renovosolutions_aws_ipam/__init__.py
renovosolutions_aws_ipam/py.typed
renovosolutions_aws_ipam/_jsii/__init__.py
renovosolutions_aws_ipam/_jsii/cdk-library-aws-ipam@0.2.0.jsii.tgz
renovosolutions_aws_cdk_aws_ipam-0.2.0.dist-info/LICENSE
renovosolutions_aws_cdk_aws_ipam-0.2.0.dist-info/METADATA
renovosolutions_aws_cdk_aws_ipam-0.2.0.dist-info/WHEEL
renovosolutions_aws_cdk_aws_ipam-0.2.0.dist-info/top_level.txt
renovosolutions_aws_cdk_aws_ipam-0.2.0.dist-info/RECORD
